.gitignore
LICENSE
MANIFEST.in
README.md
als_tracker.conf.template
conda.yaml
gunicorn_start.sh
nginx.template
pyproject.toml
src/ALSTracker/__init__.py
src/ALSTracker/_version.py
src/ALSTracker/alstracker.py
src/ALSTracker/main.py
src/ALSTracker.egg-info/PKG-INFO
src/ALSTracker.egg-info/SOURCES.txt
src/ALSTracker.egg-info/dependency_links.txt
src/ALSTracker.egg-info/requires.txt
src/ALSTracker.egg-info/top_level.txt
src/ALSTracker/doc/details.md
src/ALSTracker/doc/instructions.md
src/ALSTracker/doc/img/prior_alsfrs.png
src/ALSTracker/doc/img/prior_grip.png
src/ALSTracker/doc/img/prior_grip_sigma.png
src/ALSTracker/doc/img/prior_nfl.png
src/ALSTracker/doc/img/prior_vc.png
src/ALSTracker/doc/other/database_simulated.xlsx
src/ALSTracker/doc/other/database_template.xlsx
src/ALSTracker/templates/index.html
src/ALSTracker/templates/img/diff.png
src/ALSTracker/templates/img/distr_slope.png
src/ALSTracker/templates/img/dref.png
src/ALSTracker/templates/img/dtreat.png
src/ALSTracker/templates/img/git.png
src/ALSTracker/templates/img/nfl.png
src/ALSTracker/templates/img/progression_example.png
src/ALSTracker/templates/img/regressions.png
src/ALSTracker/templates/tools/alsfrs.html