Metadata-Version: 2.2
Name: ALSTracker
Version: 1.4.2
Summary: Bayesian ALS Tracking and Phase Evaluation
Author-email: Thorsten Wagner <thorsten.wagner@mpi-dortmund.mpg.de>, Markus Stabrin <markus.stabrin@mpi-dortmund.mpg.de>
License: Mozilla Public License Version 2.0
Project-URL: Homepage, https://alstracker.mpi-dortmund.mpg.de/
Project-URL: Issues, https://alstracker.mpi-dortmund.mpg.de/
Classifier: Programming Language :: Python :: 3
Classifier: Operating System :: OS Independent
Requires-Python: <3.13,>=3.11.9
License-File: LICENSE
Requires-Dist: pymc
Requires-Dist: bambi
Requires-Dist: statsmodels
Requires-Dist: numpy
Requires-Dist: pandas
Requires-Dist: markdown-pdf
Requires-Dist: matplotlib
Requires-Dist: seaborn
Requires-Dist: fastapi
Requires-Dist: jinja2
Requires-Dist: gunicorn
Requires-Dist: python-multipart
Requires-Dist: uvicorn
Requires-Dist: openpyxl
Requires-Dist: mogptw
